README.md
setup.py
src/VISCO2.py
src/visco2.py
src/VISCO2.egg-info/PKG-INFO
src/VISCO2.egg-info/SOURCES.txt
src/VISCO2.egg-info/dependency_links.txt
src/VISCO2.egg-info/entry_points.txt
src/VISCO2.egg-info/top_level.txt
src/visco2.egg-info/PKG-INFO
src/visco2.egg-info/SOURCES.txt
src/visco2.egg-info/dependency_links.txt
src/visco2.egg-info/entry_points.txt
src/visco2.egg-info/top_level.txt