Metadata-Version: 2.1
Name: visco2
Version: 0.0.2
Summary: Visualization of co2 emissions from 1990 to 2018 for each country
Home-page: https://github.com/Marinakanno/vis_co2
Author: marina kanno
Author-email: marinasvtmax@gmail.com
License: UNKNOWN
Project-URL: Bug Tracker, https://github.com/Marinakanno/vis_co2
Platform: UNKNOWN
Classifier: Programming Language :: Python :: 3
Classifier: License :: OSI Approved :: MIT License
Classifier: Operating System :: OS Independent
Requires-Python: >=3.7
